{
	"schemaVersion": 1,
	"id": "ballspack_mod",
	"version": "${version}",
	"name": "Ballspack Mod",
	"description": "The balls are sizable.",
	"authors": [
		"enjarai"
	],
	"contact": {
		"homepage": "https://enjarai.dev/",
		"sources": "https://github.com/enjarai/ballspack-mod"
	},
	"license": "Probably",
	"icon": "assets/ballspack_mod/icon.png",
	"environment": "*",
	"entrypoints": {
		"main": [
			"dev.enjarai.ballspackmod.BallspackMod"
		],
		"client": [
			"dev.enjarai.ballspackmod.BallspackMod"
		]
	},
	"mixins": [
		"ballspack_mod.mixins.json"
	],
	"depends": {
		"fabricloader": ">=0.15.11",
		"minecraft": "~1.21",
		"java": ">=21",
		"fabric-api": "*"
	}
}